edge_mlops_monitor/__init__.py
edge_mlops_monitor/config.py
edge_mlops_monitor/default_config.yaml
edge_mlops_monitor/drift.py
edge_mlops_monitor/model_logger.py
edge_mlops_monitor/monitor.py
edge_mlops_monitor/schema.sql
edge_mlops_monitor/system.py
edge_mlops_monitor/upload.py
edge_mlops_monitor-0.1.1.dist-info/licenses/LICENSE
examples/dummy_ml_model.py
tests/conftest.py
tests/test_config.py
tests/test_drift.py
tests/test_model_logger.py
tests/test_system.py
tests/test_upload.py
edge_mlops_monitor-0.1.1.dist-info/METADATA
edge_mlops_monitor-0.1.1.dist-info/WHEEL
edge_mlops_monitor-0.1.1.dist-info/top_level.txt
edge_mlops_monitor-0.1.1.dist-info/RECORD
