Metadata-Version: 2.4
Name: edge_mlops_monitor
Version: 0.1.1
Summary: A lightweight MLOps monitoring solution for edge devices
Author-email: Edge MLOps Monitor Contributors <edmon.sahakyan@gmail.com>
License-Expression: MIT
Project-URL: Homepage, https://github.com/Edmon02/edge-mlops-monitor
Classifier: Development Status :: 3 - Alpha
Classifier: Intended Audience :: Developers
Classifier: Programming Language :: Python :: 3.10
Classifier: Programming Language :: Python :: 3.11
Classifier: Topic :: Software Development :: Libraries :: Python Modules
Classifier: Topic :: System :: Monitoring
Requires-Python: <3.12,>=3.10
License-File: LICENSE
Requires-Dist: psutil>=5.9.0
Requires-Dist: scipy>=1.8.0
Requires-Dist: boto3>=1.24.0
Requires-Dist: PyYAML>=6.0
Dynamic: license-file
